clipboard_maximizer/__init__.py
clipboard_maximizer/cli.py
clipboard_maximizer/clipboard_manager.py
clipboard_maximizer/copy-linux-xclip.sh
clipboard_maximizer/copy-macos.applescript
clipboard_maximizer/copy-windows.ps1
clipboard_maximizer-0.2.3.dist-info/METADATA
clipboard_maximizer-0.2.3.dist-info/WHEEL
clipboard_maximizer-0.2.3.dist-info/entry_points.txt
clipboard_maximizer-0.2.3.dist-info/RECORD
