Metadata-Version: 2.1
Name: clipboard-maximizer
Version: 0.2.3
Summary: 
Author: lumpenspace
Author-email: lumpenspace@gmail.com
Requires-Python: >=3.8,<4.0
Classifier: Programming Language :: Python :: 3
Classifier: Programming Language :: Python :: 3.8
Classifier: Programming Language :: Python :: 3.9
Classifier: Programming Language :: Python :: 3.10
Classifier: Programming Language :: Python :: 3.11
Classifier: Programming Language :: Python :: 3.12
Requires-Dist: click (>=8.1.7,<9.0.0)
Requires-Dist: pytest-cov (>=4.1.0,<5.0.0)
